readwrite/__init__.py
readwrite/__main__.py
readwrite/__version__.py
readwrite/constants.py
readwrite/interactive.py
readwrite/registry.py
readwrite/utils.py
readwrite/cli/__init__.py
readwrite/cli/fast.py
readwrite/cli/manual.py
readwrite/cli/utils.py
readwrite/handlers/__init__.py
readwrite/handlers/base.py
readwrite/handlers/binary.py
readwrite/handlers/csv.py
readwrite/handlers/excel.py
readwrite/handlers/h5ad.py
readwrite/handlers/joblib.py
readwrite/handlers/json.py
readwrite/handlers/parquet.py
readwrite/handlers/pickle.py
readwrite/handlers/tar.py
readwrite/handlers/text.py
readwrite/handlers/toml.py
readwrite/handlers/yaml.py
readwrite/handlers/zarr.py
readwrite/handlers/zip.py
tests/__init__.py
tests/test_handlers.py
tests/test_interactive.py
tests/test_module.py
tests/test_registry.py
tests/test_utils.py
readwrite-0.10.0.dist-info/METADATA
readwrite-0.10.0.dist-info/WHEEL
readwrite-0.10.0.dist-info/entry_points.txt
readwrite-0.10.0.dist-info/top_level.txt
readwrite-0.10.0.dist-info/RECORD
