Metadata-Version: 2.2
Name: readwrite
Version: 0.10.0
Summary: readwrite - Quickly read/write file in common formats
Home-page: https://github.com/crunchdao/readwrite
Author: Enzo CACERES
Author-email: enzo.caceres@crunchdao.com
Keywords: package development template
Classifier: Intended Audience :: Developers
Classifier: Programming Language :: Python :: 3.7
Requires-Python: >=3
Requires-Dist: click
Requires-Dist: pyreadline3; platform_system == "Windows"
Requires-Dist: pandas
Requires-Dist: pytest
Requires-Dist: pyarrow
Requires-Dist: tqdm
Requires-Dist: pyyaml
Requires-Dist: toml
Requires-Dist: openpyxl
Requires-Dist: joblib
Dynamic: author
Dynamic: author-email
Dynamic: classifier
Dynamic: description
Dynamic: description-content-type
Dynamic: home-page
Dynamic: keywords
Dynamic: requires-dist
Dynamic: requires-python
Dynamic: summary
